ovos_audio_transformer_plugin_ggwave/__init__.py
ovos_audio_transformer_plugin_ggwave/version.py
ovos_audio_transformer_plugin_ggwave-0.0.5.dist-info/LICENSE
ovos_audio_transformer_plugin_ggwave-0.0.5.dist-info/METADATA
ovos_audio_transformer_plugin_ggwave-0.0.5.dist-info/WHEEL
ovos_audio_transformer_plugin_ggwave-0.0.5.dist-info/entry_points.txt
ovos_audio_transformer_plugin_ggwave-0.0.5.dist-info/top_level.txt
ovos_audio_transformer_plugin_ggwave-0.0.5.dist-info/zip-safe
ovos_audio_transformer_plugin_ggwave-0.0.5.dist-info/RECORD
