Metadata-Version: 2.1
Name: ovos-audio-transformer-plugin-ggwave
Version: 0.0.5
Summary: A speech lang detection plugin for mycroft
Home-page: https://github.com/OpenVoiceOS/ovos-audio-transformer-plugin-ggwave
Author: JarbasAi
Author-email: jarbasai@mailfence.com
License: Apache-2.0
Keywords: ovos plugin
Classifier: Development Status :: 3 - Alpha
Classifier: Intended Audience :: Developers
Classifier: Topic :: Text Processing :: Linguistic
Classifier: License :: OSI Approved :: Apache Software License
Classifier: Programming Language :: Python :: 2
Classifier: Programming Language :: Python :: 2.7
Classifier: Programming Language :: Python :: 3
Classifier: Programming Language :: Python :: 3.0
Classifier: Programming Language :: Python :: 3.1
Classifier: Programming Language :: Python :: 3.2
Classifier: Programming Language :: Python :: 3.3
Classifier: Programming Language :: Python :: 3.4
Classifier: Programming Language :: Python :: 3.5
Classifier: Programming Language :: Python :: 3.6
License-File: LICENSE
Requires-Dist: ovos-plugin-manager<2.0.0,>=0.0.25
Requires-Dist: ggwave<1.0.0,>=0.4.2
Requires-Dist: PyAudio~=0.2.14
